LICENSE.txt
MANIFEST.in
README.rst
setup.py
django_iron_sessions.egg-info/PKG-INFO
django_iron_sessions.egg-info/SOURCES.txt
django_iron_sessions.egg-info/dependency_links.txt
django_iron_sessions.egg-info/not-zip-safe
django_iron_sessions.egg-info/requires.txt
django_iron_sessions.egg-info/top_level.txt
iron_sessions/__init__.py
iron_sessions/session.py
iron_sessions/settings.py