Metadata-Version: 1.0
Name: django-iron-sessions
Version: 0.0.2
Summary: iron.io cache as Django sessions backend
Home-page: https://github.com/hellysmile/django-iron-sessions
Author: hellysmile
Author-email: hellysmile@gmail.com
License: http://www.apache.org/licenses/LICENSE-2.0
Keywords: django,sessions,iron cache,heroku
Platform: UNKNOWN
Classifier: Framework :: Django
Classifier: Environment :: Web Environment
Classifier: Intended Audience :: Developers
Classifier: Topic :: Internet :: WWW/HTTP
Classifier: License :: OSI Approved :: Apache Software License
Classifier: Development Status :: 5 - Production/Stable
Classifier: Natural Language :: English
Classifier: Programming Language :: Python
Classifier: Programming Language :: Python :: 2
Classifier: Programming Language :: Python :: 2.6
Classifier: Programming Language :: Python :: 2.7
Classifier: Programming Language :: Python :: 3
Classifier: Programming Language :: Python :: 3.2
Classifier: Programming Language :: Python :: 3.3
Classifier: Programming Language :: Python :: Implementation :: CPython
Classifier: Programming Language :: Python :: Implementation :: PyPy
Classifier: Operating System :: MacOS :: MacOS X
Classifier: Operating System :: Microsoft :: Windows
Classifier: Operating System :: POSIX
Classifier: Operating System :: Unix
